odoo/addons/mail_hide_body_portal_button/README.rst
odoo/addons/mail_hide_body_portal_button/__init__.py
odoo/addons/mail_hide_body_portal_button/__manifest__.py
odoo/addons/mail_hide_body_portal_button/data/config_parameter.xml
odoo/addons/mail_hide_body_portal_button/data/mail_templates.xml
odoo/addons/mail_hide_body_portal_button/models/__init__.py
odoo/addons/mail_hide_body_portal_button/models/ir_model.py
odoo/addons/mail_hide_body_portal_button/static/description/icon.png
odoo_addon_mail_hide_body_portal_button-15.0.1.0.0.1.dist-info/METADATA
odoo_addon_mail_hide_body_portal_button-15.0.1.0.0.1.dist-info/WHEEL
odoo_addon_mail_hide_body_portal_button-15.0.1.0.0.1.dist-info/top_level.txt
odoo_addon_mail_hide_body_portal_button-15.0.1.0.0.1.dist-info/RECORD
